datahugger/__init__.py
datahugger/__main__.py
datahugger/_version.py
datahugger/api.py
datahugger/base.py
datahugger/config.py
datahugger/exceptions.py
datahugger/handles.py
datahugger/metadata.py
datahugger/resolvers.py
datahugger/services.py
datahugger/utils.py
datahugger-0.13.dist-info/LICENSE
datahugger-0.13.dist-info/METADATA
datahugger-0.13.dist-info/WHEEL
datahugger-0.13.dist-info/entry_points.txt
datahugger-0.13.dist-info/top_level.txt
datahugger-0.13.dist-info/RECORD
