Metadata-Version: 2.1
Name: datahugger
Version: 0.13
Summary: One downloader for many scientific data and code repositories!
Author-email: Jonathan de Bruin <jonathandebruinos@gmail.com>
License: MIT
Classifier: Development Status :: 4 - Beta
Classifier: License :: OSI Approved :: MIT License
Classifier: Programming Language :: Python :: 3.8
Classifier: Programming Language :: Python :: 3.9
Classifier: Programming Language :: Python :: 3.10
Classifier: Programming Language :: Python :: 3.11
Classifier: Programming Language :: Python :: 3.12
Requires-Python: >=3.8
License-File: LICENSE
Requires-Dist: jsonpath_ng
Requires-Dist: requests
Requires-Dist: requests-cache
Requires-Dist: scitree
Requires-Dist: tqdm
Provides-Extra: all
Requires-Dist: datasets; extra == "all"
Provides-Extra: benchmark
Requires-Dist: pandas; extra == "benchmark"
Requires-Dist: tabulate; extra == "benchmark"
Provides-Extra: lint
Requires-Dist: ruff; extra == "lint"
Provides-Extra: test
Requires-Dist: pytest; extra == "test"
Requires-Dist: tomli; python_version < "3.11" and extra == "test"
Requires-Dist: pytest-xdist; extra == "test"
Provides-Extra: docs
Requires-Dist: mkdocs-material; extra == "docs"
